tello_zune/__init__.py
tello_zune/tello_zune.py
tello_zune-0.7.6.dist-info/licenses/LICENSE
tello_zune-0.7.6.dist-info/METADATA
tello_zune-0.7.6.dist-info/WHEEL
tello_zune-0.7.6.dist-info/top_level.txt
tello_zune-0.7.6.dist-info/RECORD
