Metadata-Version: 2.4
Name: tello_zune
Version: 0.7.6
Summary: Biblioteca tello-zune, serve para controlar, e obter informacoes do drone DJI Tello.
Home-page: https://github.com/zunedrones/tello_zune
Author: Zune Drones
Author-email: zunedrones@gmail.com
Classifier: Programming Language :: Python :: 3
Classifier: License :: OSI Approved :: GNU General Public License v3 (GPLv3)
Classifier: Operating System :: OS Independent
Requires-Python: >=3.9
License-File: LICENSE
Requires-Dist: opencv-python
Requires-Dist: numpy
Dynamic: author
Dynamic: author-email
Dynamic: classifier
Dynamic: description
Dynamic: description-content-type
Dynamic: home-page
Dynamic: license-file
Dynamic: requires-dist
Dynamic: requires-python
Dynamic: summary
